circuits/02_full_adder/src/half_adder.v
module half_adder(
    input wire a,
    input wire b,
    output wire s,
    output wire c
);

    assign s = a ^ b;
    assign c = a & b;

endmodule

circuits/02_full_adder/src/full_adder.v
module full_adder(
    input wire a,
    input wire b,
    input wire cin,
    output wire s,
    output wire cout
);

    wire partial_sum;
    wire carry_ab;
    wire carry_cin;

    half_adder first(
        .a(a),
        .b(b),
        .s(partial_sum),
        .c(carry_ab)
    );

    half_adder second(
        .a(partial_sum),
        .b(cin),
        .s(s),
        .c(carry_cin)
    );

    assign cout = carry_ab | carry_cin;

endmodule

circuits/02_full_adder/sim/tb_full_adder.sv
`timescale 1ns/1ps

module tb_full_adder;

    reg a, b, cin;
    wire s, cout;

    full_adder dut(a, b, cin, s, cout);

    integer n, checked = 0;
    reg [1:0] expected;

    initial begin
        $dumpfile("wave.vcd");
        $dumpvars(0, tb_full_adder);

        for(n = 0; n < 8; n = n + 1) begin
            {a, b, cin} = n;
            expected = a + b + cin;
            #10;

            if({cout, s} !== expected)
                $fatal(1,
                    "FAIL full_adder vector=%0d expected=%b actual=%b",
                    n, expected, {cout, s});

            checked = checked + 1;
        end

        if(checked != 8)
            $fatal(1, "Incomplete test");

        $display("LAB1_PASS full_adder cases=%0d", checked);
        $finish;
    end

    initial begin
        #100000;
        $fatal(1, "Watchdog");
    end

endmodule

evidence/02/vscode/wave.vcd
$date
	Mon Sep 14 11:46:23 2026
$end
$version
	Icarus Verilog
$end
$timescale
	1ps
$end
$scope module tb_full_adder $end
$var wire 1 ! s $end
$var wire 1 " cout $end
$var reg 1 # a $end
$var reg 1 $ b $end
$var reg 1 % cin $end
$var reg 2 & expected [1:0] $end
$var integer 32 ' checked [31:0] $end
$var integer 32 ( n [31:0] $end
$scope module dut $end
$var wire 1 # a $end
$var wire 1 $ b $end
$var wire 1 % cin $end
$var wire 1 " cout $end
$var wire 1 ! s $end
$var wire 1 ) partial_sum $end
$var wire 1 * carry_cin $end
$var wire 1 + carry_ab $end
$scope module first $end
$var wire 1 # a $end
$var wire 1 $ b $end
$var wire 1 + c $end
$var wire 1 ) s $end
$upscope $end
$scope module second $end
$var wire 1 ) a $end
$var wire 1 % b $end
$var wire 1 * c $end
$var wire 1 ! s $end
$upscope $end
$upscope $end
$upscope $end
$enddefinitions $end
$comment Show the parameter values. $end
$dumpall
$end
#0
$dumpvars
0+
0*
0)
b0 (
b0 '
b0 &
0%
0$
0#
0"
0!
$end
#10000
1!
b1 &
1%
b1 (
b1 '
#20000
1)
1!
1$
0%
b10 (
b10 '
#30000
1"
0!
1*
b10 &
1%
b11 (
b11 '
#40000
0"
1!
0*
b1 &
1#
0$
0%
b100 (
b100 '
#50000
1"
0!
1*
b10 &
1%
b101 (
b101 '
#60000
0)
1+
0!
0*
1$
0%
b110 (
b110 '
#70000
1!
b11 &
1%
b111 (
b111 '
#80000
b1000 (
b1000 '
